brunnhilde.py
brunnhilde-1.9.6.data/scripts/brunnhilde.py
brunnhilde-1.9.6.dist-info/LICENSE
brunnhilde-1.9.6.dist-info/METADATA
brunnhilde-1.9.6.dist-info/WHEEL
brunnhilde-1.9.6.dist-info/top_level.txt
brunnhilde-1.9.6.dist-info/RECORD
