Metadata-Version: 2.1
Name: brunnhilde
Version: 1.9.6
Summary: A Siegfried-based digital archives reporting tool for directories and disk images
Home-page: https://github.com/tw4l/brunnhilde
Author: Tessa Walsh
Author-email: tessa@bitarchivist.net
Keywords: archives reporting characterization identification diskimages
Platform: POSIX
Platform: Windows
Classifier: Development Status :: 5 - Production/Stable
Classifier: License :: OSI Approved :: MIT License
Classifier: Intended Audience :: End Users/Desktop
Classifier: Intended Audience :: Developers
Classifier: Natural Language :: English
Classifier: Operating System :: MacOS
Classifier: Operating System :: MacOS :: MacOS X
Classifier: Operating System :: POSIX :: Linux
Classifier: Operating System :: Microsoft :: Windows
Classifier: Programming Language :: Python :: 2.7
Classifier: Programming Language :: Python :: 3.5
Classifier: Programming Language :: Python :: 3.6
Classifier: Programming Language :: Python :: 3.7
Classifier: Programming Language :: Python :: 3.8
Classifier: Topic :: System :: Archiving
Classifier: Topic :: System :: Filesystems
Classifier: Topic :: Utilities
License-File: LICENSE
